{
  "search:gitlab-ci:gitlab ci stages artifacts cac": {
    "content": "- Use `gitlab-runner` to install and configure GitLab Runner.\n- Set up cache in `.gitlab-ci.yml` using the `cache` keyword.\n- Utilize artifacts for passing build results between jobs with the `artifacts` keyword.\n- For Docker builds, enable caching by using multi-stage builds and leveraging Docker's built-in caching mechanism.\n- Ensure your GitLab Runner has access to a Docker registry for pulling and pushing images.\n- Check the latest versions of GitLab CI/CD features on the [GitLab Documentation](https://docs.gitlab.com/ee/ci/) page.\n- Configure cache storage options in `.gitlab-ci.yml` using `cache:policy`, `cache:key`, and `cache:untracked`.\n- For distributed caching, enable S3 or another supported backend in GitLab Runner configuration.",
    "source": "web_search",
    "updated_at": 1781056287.5976877
  },
  "search:gitlab-ci:gitlab ci stages artifacts cac_ex": {
    "content": "- **CLI Commands**:\n  - `gitlab-ci` for managing CI/CD configurations.\n  - `docker build --cache-from <image>` to use a cache image.\n  - `docker push <image>` to push an image to the GitLab registry.\n\n- **Latest Versions**:\n  - GitLab: Latest stable version as of my last update.\n  - Docker: Latest stable version as of my last update.\n\n- **Key Config Options**:\n  - `.gitlab-ci.yml`: Defines CI/CD pipeline stages and jobs.\n  - `stages`: Specifies the sequence of jobs to run.\n  - `cache`: Configures caching for speeding up builds.\n  - `services`: Declares Docker services needed by jobs.\n  - `image`: Specifies the Docker image used for the job.",
    "source": "code_example",
    "updated_at": 1780966431.9872482
  }
}